lpro_s/__init__.py
lpro_s/scripts/__init__.py
lpro_s/scripts/lpro_s.py
lpro_s-1.1.5.dist-info/licenses/LICENSE
lpro_s-1.1.5.dist-info/METADATA
lpro_s-1.1.5.dist-info/WHEEL
lpro_s-1.1.5.dist-info/entry_points.txt
lpro_s-1.1.5.dist-info/top_level.txt
lpro_s-1.1.5.dist-info/RECORD
